b64_cli/__init__.py
b64_cli/main.py
b64_cli_tool-0.1.1.dist-info/licenses/LICENSE
b64_cli_tool-0.1.1.dist-info/METADATA
b64_cli_tool-0.1.1.dist-info/WHEEL
b64_cli_tool-0.1.1.dist-info/entry_points.txt
b64_cli_tool-0.1.1.dist-info/top_level.txt
b64_cli_tool-0.1.1.dist-info/RECORD
